tests/__init__.py
tests/test_env_options.py
tests/test_main.py
text_to_gif/__init__.py
text_to_gif/emoji_check.py
text_to_gif/env_options.py
text_to_gif/gif_creator.py
text_to_gif/image_file_filter.py
text_to_gif/main.py
text_to_gif/setting.py
text_to_gif/text2gif.py
text_to_gif-0.0.9.dist-info/METADATA
text_to_gif-0.0.9.dist-info/WHEEL
text_to_gif-0.0.9.dist-info/entry_points.txt
text_to_gif-0.0.9.dist-info/top_level.txt
text_to_gif-0.0.9.dist-info/RECORD
